static_frame/__init__.py
static_frame/__main__.py
static_frame/py.typed
static_frame/core/__init__.py
static_frame/core/archive_npy.py
static_frame/core/archive_zip.py
static_frame/core/assign.py
static_frame/core/axis_map.py
static_frame/core/batch.py
static_frame/core/bus.py
static_frame/core/container.py
static_frame/core/container_util.py
static_frame/core/db_util.py
static_frame/core/display.py
static_frame/core/display_color.py
static_frame/core/display_config.py
static_frame/core/display_html_datatables.py
static_frame/core/display_visidata.py
static_frame/core/doc_str.py
static_frame/core/exception.py
static_frame/core/fill_value_auto.py
static_frame/core/frame.py
static_frame/core/generic_aliases.py
static_frame/core/hloc.py
static_frame/core/index.py
static_frame/core/index_auto.py
static_frame/core/index_base.py
static_frame/core/index_correspondence.py
static_frame/core/index_datetime.py
static_frame/core/index_hierarchy.py
static_frame/core/index_hierarchy_set_utils.py
static_frame/core/interface.py
static_frame/core/interface_meta.py
static_frame/core/join.py
static_frame/core/loc_map.py
static_frame/core/memory_measure.py
static_frame/core/metadata.py
static_frame/core/node_dt.py
static_frame/core/node_fill_value.py
static_frame/core/node_hashlib.py
static_frame/core/node_iter.py
static_frame/core/node_re.py
static_frame/core/node_selector.py
static_frame/core/node_str.py
static_frame/core/node_transpose.py
static_frame/core/node_values.py
static_frame/core/pivot.py
static_frame/core/platform.py
static_frame/core/protocol_dfi.py
static_frame/core/protocol_dfi_abc.py
static_frame/core/quilt.py
static_frame/core/rank.py
static_frame/core/reduce.py
static_frame/core/series.py
static_frame/core/series_mapping.py
static_frame/core/sort_interface.py
static_frame/core/store.py
static_frame/core/store_client_mixin.py
static_frame/core/store_config.py
static_frame/core/store_filter.py
static_frame/core/store_sqlite.py
static_frame/core/store_xlsx.py
static_frame-3.4.0.dist-info/licenses/LICENSE.txt
static_frame-3.4.0.dist-info/METADATA
static_frame-3.4.0.dist-info/WHEEL
static_frame-3.4.0.dist-info/top_level.txt
static_frame-3.4.0.dist-info/RECORD
