Metadata-Version: 2.4
Name: static-frame
Version: 3.4.0
Summary: Immutable and statically-typeable DataFrames with runtime type and data validation.
Home-page: https://github.com/static-frame/static-frame
Author: Christopher Ariza
License: MIT
Keywords: staticframe pandas numpy immutable array
Classifier: Development Status :: 5 - Production/Stable
Classifier: Intended Audience :: Developers
Classifier: Topic :: Software Development
Classifier: Topic :: Scientific/Engineering
Classifier: Topic :: Scientific/Engineering :: Information Analysis
Classifier: License :: OSI Approved :: MIT License
Classifier: Operating System :: MacOS :: MacOS X
Classifier: Operating System :: Microsoft :: Windows
Classifier: Operating System :: POSIX
Classifier: Programming Language :: Python :: 3.10
Classifier: Programming Language :: Python :: 3.11
Classifier: Programming Language :: Python :: 3.12
Classifier: Programming Language :: Python :: 3.13
Classifier: Programming Language :: Python :: Free Threading
Classifier: Intended Audience :: Developers
Classifier: Intended Audience :: Information Technology
Classifier: Intended Audience :: Science/Research
Classifier: Typing :: Typed
Requires-Python: >=3.10
License-File: LICENSE.txt
Requires-Dist: numpy>=1.23.5
Requires-Dist: arraykit==1.1.0
Requires-Dist: typing-extensions>=4.12.0
Provides-Extra: extras
Requires-Dist: pandas>=1.1.5; extra == "extras"
Requires-Dist: xlsxwriter>=1.1.2; extra == "extras"
Requires-Dist: openpyxl>=3.0.9; extra == "extras"
Requires-Dist: xarray>=0.13.0; extra == "extras"
Requires-Dist: pyarrow>=3.0.0; extra == "extras"
Requires-Dist: visidata>=2.4; extra == "extras"
Dynamic: author
Dynamic: classifier
Dynamic: description
Dynamic: description-content-type
Dynamic: home-page
Dynamic: keywords
Dynamic: license
Dynamic: license-file
Dynamic: provides-extra
Dynamic: requires-dist
Dynamic: requires-python
Dynamic: summary
